<configuration name="switch.conf" description="Core Configuration">
                  
	<cli-keybindings>
		<key name="1" value="help"/>
		<key name="2" value="status"/>
		<key name="3" value="show channels"/>
		<key name="4" value="show calls"/>
		<key name="5" value="sofia status"/>
		<key name="6" value="reloadxml"/>
		<key name="7" value="console loglevel 0"/>
		<key name="8" value="console loglevel 7"/>
		<key name="9" value="sofia status profile internal"/>
		<key name="10" value="sofia profile internal siptrace on"/>
		<key name="11" value="sofia profile internal siptrace off"/>
		<key name="12" value="version"/>
	</cli-keybindings> 
	
	<default-ptimes>
		<!-- Set this to override the 20ms assumption of various codecs in the sdp with no ptime defined -->
		<!-- <codec name="G729" ptime="40"/> -->
	</default-ptimes>
  
	<settings>     
		<!--Try to catch any crashes that can be recoverable (in the context of a call)-->
		<param name="crash-protection" value="false"/>	
		<!--Most channels to allow at once -->
		<param name="max-sessions" value="$${max_sessions}"/>	
		<!--Most channels to create per second -->
		<param name="sessions-per-second" value="$${max_cps}"/>       
		<param name="core-db-name" value="/dev/shm/core.db" /> 
		<!--RTP port range -->
		<!--<param name="rtp-start-port" value="16384"/>-->
		<!--<param name="rtp-end-port" value="32768"/>-->		
	</settings>

</configuration>